Workbook

Sheet Summary
A1: NSE Short ATM Straddle — Paper Trade
A2: Week 1 (16-22 Sep) · NIFTY · intraday (sell at open, cover at close) · real NSE F&O exchange prices
A4: NET PROFIT | B4: =SUM('Trade Log'!$O$5:$O$14) | C4: on peak margin of | D4: =MAX(Daily!$D$4:$D$8) | E4: =IFERROR(B4/D4,0)
A6: Metric | B6: Value
A7: Trades | B7: =COUNT('Trade Log'!$O$5:$O$14)
A8: Winning trades | B8: =COUNTIF('Trade Log'!$O$5:$O$14,">0")
A9: Losing trades | B9: =COUNTIF('Trade Log'!$O$5:$O$14,"<=0")
A10: Win rate | B10: =IFERROR(B8/B7,0)
A11: Sessions traded | B11: =COUNT(Daily!$C$4:$C$8)
A12: Winning sessions | B12: =COUNTIF(Daily!$C$4:$C$8,">0")
A13: Gross P&L ₹ | B13: =SUM('Trade Log'!$M$5:$M$14)
A14: Total costs ₹ | B14: =SUM('Trade Log'!$N$5:$N$14)
A15: NET P&L ₹ | B15: =SUM('Trade Log'!$O$5:$O$14)
A16: Best trade ₹ | B16: =MAX('Trade Log'!$O$5:$O$14)
A17: Worst trade ₹ | B17: =MIN('Trade Log'!$O$5:$O$14)
A18: Average trade ₹ | B18: =IFERROR(AVERAGE('Trade Log'!$O$5:$O$14),0)
A19: Peak margin ₹ | B19: =MAX(Daily!$D$4:$D$8)
A20: Return on peak margin | B20: =IFERROR(B15/B19,0)
A22: What happened this week
A23: • NIFTY barely moved: 23,201.60 to 23,329.00 across the whole week, +0.55%, with a largest single-day move of 0.36%.
A24: • A short straddle is a bet on stillness, not a forecast. It collects premium when price sits still, so a near-motionless week is close to its best case.
A25: • All five sessions were positive and 7 of the 10 legs made money.
A26: • CONTEXT — this is one selected week from an eight-month record. The following week (23-29 Sep) lost ₹39,140 on the same rules when the market fell 2-4%. Over the eight-month backtest the strategy earned ₹45,470 with a maximum drawdown of ₹94,210.
A28: NOT INVESTMENT ADVICE. A paper trade on historical exchange data. Real fills, slippage and margin calls will differ from these figures.

Sheet Assumptions
A1: Short ATM Straddle — Assumptions & Method
A2: Yellow cells drive every figure in this workbook. Change one and the model recalculates.
A4: Parameter | B4: Value | C4: Unit | D4: Source / note
A5: Margin requirement | B5: 0.12 | C5: of notional | D5: SPAN + exposure on a short index option, approximate. Broker-specific — confirm with yours.
A6: Cost per lot (round trip) | B6: 60 | C6: ₹ | D6: Brokerage + STT + exchange fees + GST + stamp duty, one lot in and out, discount broker.
A7: NIFTY lot size | B7: 75 | C7: units | D7: NSE contract specification.
A8: BANKNIFTY lot size | B8: 35 | C8: units | D8: NSE contract specification (no BANKNIFTY trades this week).
A9: Max days to expiry | B9: 7 | C9: days | D9: Strategy rule — weekly contracts only.
A10: ATM band | B10: 0.005 | C10: of spot | D10: Strike within ±0.5% of the PRIOR session close.
A11: Min prior-session volume | B11: 1000 | C11: contracts | D11: Liquidity filter on the PREVIOUS session. Never same-day volume, which is look-ahead.
A14: Method
A15: • At the open, SELL the at-the-money call and the at-the-money put.
A16: • Strike chosen from the PRIOR session close — the only spot a trader knows at the open.
A17: • Liquidity filtered on the PRIOR session volume, never the current day's.
A18: • Cover both legs at the close. No position held overnight.
A19: • Prices are real NSE exchange data (daily F&O bhavcopy), not modelled.
A21: Data integrity — three look-ahead leaks were removed before these numbers
A22: • Selecting contracts by SAME-DAY volume, which is only known at the close. Worth 25x in P&L.
A23: • UndrlygPric in the bhavcopy is the CLOSING spot (verified at 0.0000% difference against the NIFTY close), so choosing 'ATM' with it picks the strike that ENDED at the money — exactly the strike that decayed most that day.
A24: • Testing only a calm window. With the leaks present the backtest showed Sharpe 17.51; corrected, it is Sharpe 1.27.

Sheet Trade Log
A1: Trade Log — Week 1 (16-22 Sep)
A2: Real NSE exchange prices. Blue = raw exchange data, black = formula, green = link to Assumptions.
A4: Date | B4: Symbol | C4: C/P | D4: Expiry | E4: DTE | F4: Strike | G4: Prior close | H4: Spot (close) | I4: Sell @ open | J4: Buy @ close | K4: Points | L4: Lot | M4: Gross ₹ | N4: Cost ₹ | O4: Net P&L ₹ | P4: Margin ₹ | Q4: % of margin
A5: 46281 | B5: NIFTY | C5: CE | D5: 46287 | E5: 6 | F5: 23100 | G5: 23118.6 | H5: 23217.6 | I5: 246.05 | J5: 242.5 | K5: =I5-J5 | L5: 75 | M5: =K5*L5 | N5: =Assumptions!$B$6 | O5: =M5-N5 | P5: =G5*L5*Assumptions!$B$5 | Q5: =IFERROR(O5/P5,0)
A6: 46281 | B6: NIFTY | C6: PE | D6: 46287 | E6: 6 | F6: 23100 | G6: 23118.6 | H6: 23217.6 | I6: 120 | J6: 99.15 | K6: =I6-J6 | L6: 75 | M6: =K6*L6 | N6: =Assumptions!$B$6 | O6: =M6-N6 | P6: =G6*L6*Assumptions!$B$5 | Q6: =IFERROR(O6/P6,0)
A7: 46282 | B7: NIFTY | C7: CE | D7: 46287 | E7: 5 | F7: 23200 | G7: 23217.6 | H7: 23270.6 | I7: 159 | J7: 183 | K7: =I7-J7 | L7: 75 | M7: =K7*L7 | N7: =Assumptions!$B$6 | O7: =M7-N7 | P7: =G7*L7*Assumptions!$B$5 | Q7: =IFERROR(O7/P7,0)
A8: 46282 | B8: NIFTY | C8: PE | D8: 46287 | E8: 5 | F8: 23200 | G8: 23217.6 | H8: 23270.6 | I8: 135 | J8: 72.35 | K8: =I8-J8 | L8: 75 | M8: =K8*L8 | N8: =Assumptions!$B$6 | O8: =M8-N8 | P8: =G8*L8*Assumptions!$B$5 | Q8: =IFERROR(O8/P8,0)
A9: 46283 | B9: NIFTY | C9: CE | D9: 46287 | E9: 4 | F9: 23250 | G9: 23270.6 | H9: 23346.4 | I9: 165.95 | J9: 154.55 | K9: =I9-J9 | L9: 75 | M9: =K9*L9 | N9: =Assumptions!$B$6 | O9: =M9-N9 | P9: =G9*L9*Assumptions!$B$5 | Q9: =IFERROR(O9/P9,0)
A10: 46283 | B10: NIFTY | C10: PE | D10: 46287 | E10: 4 | F10: 23250 | G10: 23270.6 | H10: 23346.4 | I10: 77.85 | J10: 49.4 | K10: =I10-J10 | L10: 75 | M10: =K10*L10 | N10: =Assumptions!$B$6 | O10: =M10-N10 | P10: =G10*L10*Assumptions!$B$5 | Q10: =IFERROR(O10/P10,0)
A11: 46286 | B11: NIFTY | C11: CE | D11: 46287 | E11: 1 | F11: 23350 | G11: 23346.4 | H11: 23414.3 | I11: 79 | J11: 124.75 | K11: =I11-J11 | L11: 75 | M11: =K11*L11 | N11: =Assumptions!$B$6 | O11: =M11-N11 | P11: =G11*L11*Assumptions!$B$5 | Q11: =IFERROR(O11/P11,0)
A12: 46286 | B12: NIFTY | C12: PE | D12: 46287 | E12: 1 | F12: 23350 | G12: 23346.4 | H12: 23414.3 | I12: 89 | J12: 32.2 | K12: =I12-J12 | L12: 75 | M12: =K12*L12 | N12: =Assumptions!$B$6 | O12: =M12-N12 | P12: =G12*L12*Assumptions!$B$5 | Q12: =IFERROR(O12/P12,0)
A13: 46287 | B13: NIFTY | C13: CE | D13: 46287 | E13: 0 | F13: 23400 | G13: 23414.3 | H13: 23329 | I13: 84.75 | J13: 6.75 | K13: =I13-J13 | L13: 75 | M13: =K13*L13 | N13: =Assumptions!$B$6 | O13: =M13-N13 | P13: =G13*L13*Assumptions!$B$5 | Q13: =IFERROR(O13/P13,0)
A14: 46287 | B14: NIFTY | C14: PE | D14: 46287 | E14: 0 | F14: 23400 | G14: 23414.3 | H14: 23329 | I14: 27 | J14: 62.7 | K14: =I14-J14 | L14: 75 | M14: =K14*L14 | N14: =Assumptions!$B$6 | O14: =M14-N14 | P14: =G14*L14*Assumptions!$B$5 | Q14: =IFERROR(O14/P14,0)
A15: TOTAL | M15: =SUM(M5:M14) | N15: =SUM(N5:N14) | O15: =SUM(O5:O14)

Sheet Daily
A1: Daily Summary — Week 1 (16-22 Sep)
A3: Date | B3: Positions | C3: Net P&L ₹ | D3: Margin ₹ | E3: % of margin | F3: Cumulative ₹
A4: 46281 | B4: =COUNTIF('Trade Log'!$A$5:$A$14,$A4) | C4: =SUMIF('Trade Log'!$A$5:$A$14,$A4,'Trade Log'!$O$5:$O$14) | D4: =SUMIF('Trade Log'!$A$5:$A$14,$A4,'Trade Log'!$P$5:$P$14) | E4: =IFERROR(C4/D4,0) | F4: =SUM($C$4:C4)
A5: 46282 | B5: =COUNTIF('Trade Log'!$A$5:$A$14,$A5) | C5: =SUMIF('Trade Log'!$A$5:$A$14,$A5,'Trade Log'!$O$5:$O$14) | D5: =SUMIF('Trade Log'!$A$5:$A$14,$A5,'Trade Log'!$P$5:$P$14) | E5: =IFERROR(C5/D5,0) | F5: =SUM($C$4:C5)
A6: 46283 | B6: =COUNTIF('Trade Log'!$A$5:$A$14,$A6) | C6: =SUMIF('Trade Log'!$A$5:$A$14,$A6,'Trade Log'!$O$5:$O$14) | D6: =SUMIF('Trade Log'!$A$5:$A$14,$A6,'Trade Log'!$P$5:$P$14) | E6: =IFERROR(C6/D6,0) | F6: =SUM($C$4:C6)
A7: 46286 | B7: =COUNTIF('Trade Log'!$A$5:$A$14,$A7) | C7: =SUMIF('Trade Log'!$A$5:$A$14,$A7,'Trade Log'!$O$5:$O$14) | D7: =SUMIF('Trade Log'!$A$5:$A$14,$A7,'Trade Log'!$P$5:$P$14) | E7: =IFERROR(C7/D7,0) | F7: =SUM($C$4:C7)
A8: 46287 | B8: =COUNTIF('Trade Log'!$A$5:$A$14,$A8) | C8: =SUMIF('Trade Log'!$A$5:$A$14,$A8,'Trade Log'!$O$5:$O$14) | D8: =SUMIF('Trade Log'!$A$5:$A$14,$A8,'Trade Log'!$P$5:$P$14) | E8: =IFERROR(C8/D8,0) | F8: =SUM($C$4:C8)
A9: TOTAL | B9: =SUM(B4:B8) | C9: =SUM(C4:C8)
